{"result":{"content":"<h1>Lurin Dynasty</h1>\n<ul>\n<li>Rulers of the <a class=\"   \" href=\"/dnd/eos-rising/places/lurin-empire\">Lurin Empire</a></li>\n<li>Run by three individuals, each representing a different god in the order\n<ul>\n<li>Orsoth: The Sun, Creation</li>\n<li>Alura: The Earth, Life</li>\n<li>Enebris: The Non, Death</li>\n</ul>\n</li>\n<li>Theocracy</li>\n<li>Against any other religions in the empire</li>\n</ul>","data":{"alias":["Lurin Dynasty","The Lurin Dynasty"],"tags":["Eos"]},"excerpt":""}}